README.rst
setup.py
metraj/__init__.py
metraj/trajectory.py
metraj/util.py
metraj.egg-info/PKG-INFO
metraj.egg-info/SOURCES.txt
metraj.egg-info/dependency_links.txt
metraj.egg-info/requires.txt
metraj.egg-info/top_level.txt
metraj/compute/__init__.py
metraj/compute/pointwise.py
metraj/compute/trajectory.py
metraj/graphics/__init__.py
metraj/graphics/d3.py
metraj/graphics/simple_plots.py
metraj/graphics/util.py
metraj/measurement/__init__.py
metraj/shortcuts/__init__.py
metraj/shortcuts/filt.py
metraj/smoothing/__init__.py
metraj/smoothing/segment.py
metraj/smoothing/simple.py
metraj/trajgen/__init__.py
metraj/trajgen/generate.py